
    {
      "blocks": [
        {
          "word": "I think that the best way to be successful in life is to do what you’re passionate about.",
          "transcription": "",
          "translations": [
            "Я думаю, что лучший способ быть успешным в жизни это делать то, чем вы увлечены."
          ]
        }
      ],
      "en": "I think that the best way to be successful in life is to do what you’re passionate about.",
      "ru": "Я думаю, что лучший способ быть успешным в жизни это делать то, чем вы увлечены.",
      "transcription": "",
      "yaTranslation": "Я думаю, что лучший способ быть успешным в жизни это делать то, чем вы увлечены."
    }
  